uv_development_toggle/__init__.py
uv_development_toggle-0.6.0.dist-info/METADATA
uv_development_toggle-0.6.0.dist-info/WHEEL
uv_development_toggle-0.6.0.dist-info/entry_points.txt
uv_development_toggle-0.6.0.dist-info/RECORD
