Metadata-Version: 2.4
Name: uv-development-toggle
Version: 0.6.0
Summary: Easily toggle between development and production packages with uv. Quickly close development packages locally.
Project-URL: Repository, https://github.com/iloveitaly/uv-development-toggle
Author-email: Michael Bianco <mike@mikebian.co>
Keywords: development,package,uv
Requires-Python: >=3.9
Requires-Dist: rich>=13.9.4
Requires-Dist: tomlkit>=0.13.2
